theblockchainapi/__init__.py
theblockchainapi/api_resource.py
theblockchainapi/developer_program_resource.py
theblockchainapi/resource.py
theblockchainapi-0.0.604.dist-info/LICENSE
theblockchainapi-0.0.604.dist-info/METADATA
theblockchainapi-0.0.604.dist-info/WHEEL
theblockchainapi-0.0.604.dist-info/top_level.txt
theblockchainapi-0.0.604.dist-info/RECORD
