Metadata-Version: 2.1
Name: theblockchainapi
Version: 0.0.604
Summary: Blockchain made easy. Find out more at docs.blockchainapi.com.
Home-page: https://github.com/BL0CK-X/the-blockchain-api
Author: Blockchain API
Author-email: info@blockchainapi.com
License: UNKNOWN
Platform: UNKNOWN
Classifier: Programming Language :: Python :: 3
Classifier: License :: OSI Approved :: MIT License
Classifier: Operating System :: OS Independent
Requires-Python: >=3.6
License-File: LICENSE
